vapl_interpreter/__init__.py
vapl_interpreter/errors.py
vapl_interpreter-0.2.2.dist-info/METADATA
vapl_interpreter-0.2.2.dist-info/WHEEL
vapl_interpreter-0.2.2.dist-info/top_level.txt
vapl_interpreter-0.2.2.dist-info/RECORD
