Metadata-Version: 2.1
Name: vapl-interpreter
Version: 0.2.2
Summary: An interpreter for VAPL
Home-page: https://replit.com/@WWWtheW/vaplinterpreter#README.md
Author: WWWtheW
Author-email: dontemailme@heheehheeeeeeeeeeeeeheehehehehe.com
License: MIT
Platform: UNKNOWN
